JornadaRPA/__init__.py
JornadaRPA/AgentAI/__init__.py
JornadaRPA/AgentAI/agent.py
JornadaRPA/AgentAI/memory.py
JornadaRPA/AgentAI/providers.py
JornadaRPA/AgentAI/providers_base.py
JornadaRPA/AgentAI/memory/json_memory.py
JornadaRPA/AgentAI/providers/__init__.py
JornadaRPA/AgentAI/providers/anthropic_provider.py
JornadaRPA/AgentAI/providers/gemini_provider.py
JornadaRPA/AgentAI/providers/huggingface_provider.py
JornadaRPA/AgentAI/providers/mistral_provider.py
JornadaRPA/AgentAI/providers/ollama_provider.py
JornadaRPA/AgentAI/providers/openai_provider.py
JornadaRPA/AgentAI/tools/__init__.py
JornadaRPA/AgentAI/tools/tools_basic.py
jornadarpa_agentai-0.1.3.dist-info/METADATA
jornadarpa_agentai-0.1.3.dist-info/WHEEL
jornadarpa_agentai-0.1.3.dist-info/top_level.txt
jornadarpa_agentai-0.1.3.dist-info/RECORD
