Metadata-Version: 2.4
Name: JornadaRPA.AgentAI
Version: 0.1.3
Summary: Agent AI for RPA using multiple LLM providers
Author-email: Alex Diogo <alexdiogo@desafiosrpa.com.br>
Requires-Python: >=3.8
Provides-Extra: openai
Requires-Dist: openai>=1.98.0; extra == "openai"
Provides-Extra: anthropic
Requires-Dist: anthropic>=0.20.0; extra == "anthropic"
Provides-Extra: mistral
Requires-Dist: transformers>=4.40.0; extra == "mistral"
Requires-Dist: torch; extra == "mistral"
Provides-Extra: huggingface
Requires-Dist: transformers>=4.40.0; extra == "huggingface"
Requires-Dist: torch; extra == "huggingface"
Provides-Extra: gemini
Requires-Dist: google-generativeai>=0.3.2; extra == "gemini"
Provides-Extra: all
Requires-Dist: openai>=1.0.0; extra == "all"
Requires-Dist: anthropic>=0.20.0; extra == "all"
Requires-Dist: transformers>=4.40.0; extra == "all"
Requires-Dist: torch; extra == "all"
Requires-Dist: google-generativeai>=0.3.2; extra == "all"
